berhoel/__init__.py
berhoel/cmd_line_history/__init__.py
berhoel/cmd_line_history/history.py
berhoel/cmd_line_history/irl_completer.py
berhoel/cmd_line_history/py.typed
berhoel/cmd_line_history/test/.ruff.toml
berhoel/cmd_line_history/test/test_cmd_line_history.py
pycmdlinehistory-1.1.6.dist-info/LICENSE
pycmdlinehistory-1.1.6.dist-info/METADATA
pycmdlinehistory-1.1.6.dist-info/WHEEL
pycmdlinehistory-1.1.6.dist-info/RECORD
