Metadata-Version: 2.1
Name: pyCmdlineHistory
Version: 1.1.6
Summary: Save command line history and provide a command line completer for python.
Home-page: https://python.xn--hllmanns-n4a.de/pyCmdlineHistory/
License: CC-BY-SA-4.0
Author: Sunjoong LEE
Author-email: sunjoong@gmail.com
Requires-Python: >=3.10,<4.0
Classifier: Development Status :: 5 - Production/Stable
Classifier: Environment :: Console
Classifier: Intended Audience :: End Users/Desktop
Classifier: Intended Audience :: System Administrators
Classifier: License :: Other/Proprietary License
Classifier: Operating System :: POSIX
Classifier: Programming Language :: Python :: 3
Classifier: Programming Language :: Python :: 3.10
Classifier: Programming Language :: Python :: 3.11
Classifier: Programming Language :: Python :: 3.12
Classifier: Topic :: System :: Shells
Classifier: Topic :: Utilities
Requires-Dist: setuptools
Project-URL: Documentation, https://python.xn--hllmanns-n4a.de/pyCmdlineHistory/
Project-URL: Repository, https://gitlab.com/berhoel/python/pyCmdlineHistory.git
